z3c.dependencychecker-2.14.3-py3.8-nspkg.pth
z3c/dependencychecker/USAGE.rst
z3c/dependencychecker/__init__.py
z3c/dependencychecker/db.py
z3c/dependencychecker/dotted_name.py
z3c/dependencychecker/main.py
z3c/dependencychecker/modules.py
z3c/dependencychecker/package.py
z3c/dependencychecker/report.py
z3c/dependencychecker/utils.py
z3c/dependencychecker/tests/__init__.py
z3c/dependencychecker/tests/conftest.py
z3c/dependencychecker/tests/test_dotted_name.py
z3c/dependencychecker/tests/test_dotted_name_containment.py
z3c/dependencychecker/tests/test_imports_database.py
z3c/dependencychecker/tests/test_integration.py
z3c/dependencychecker/tests/test_main.py
z3c/dependencychecker/tests/test_modules_base.py
z3c/dependencychecker/tests/test_modules_django_settings.py
z3c/dependencychecker/tests/test_modules_docfiles.py
z3c/dependencychecker/tests/test_modules_docstrings.py
z3c/dependencychecker/tests/test_modules_fti.py
z3c/dependencychecker/tests/test_modules_gs_metadata.py
z3c/dependencychecker/tests/test_modules_python.py
z3c/dependencychecker/tests/test_modules_zcml.py
z3c/dependencychecker/tests/test_package.py
z3c/dependencychecker/tests/test_package_metadata.py
z3c/dependencychecker/tests/test_report.py
z3c/dependencychecker/tests/test_user_mappings.py
z3c/dependencychecker/tests/utils.py
z3c/dependencychecker/tests/sample1/setup.py_in
z3c/dependencychecker/tests/sample1/src/sample1/__init__.py_in
z3c/dependencychecker/tests/sample1/src/sample1/configure.zcml_in
z3c/dependencychecker/tests/sample1/src/sample1/djangosettings.py_in
z3c/dependencychecker/tests/sample1/src/sample1/fromimports.py_in
z3c/dependencychecker/tests/sample1/src/sample1/ftesting.zcml_in
z3c/dependencychecker/tests/sample1/src/sample1/future_imports.py_in
z3c/dependencychecker/tests/sample1/src/sample1/import_as.py_in
z3c/dependencychecker/tests/sample1/src/sample1/import_asterisk.py_in
z3c/dependencychecker/tests/sample1/src/sample1/missingrequirements.py_in
z3c.dependencychecker-2.14.3.dist-info/LICENSE.rst
z3c.dependencychecker-2.14.3.dist-info/METADATA
z3c.dependencychecker-2.14.3.dist-info/WHEEL
z3c.dependencychecker-2.14.3.dist-info/entry_points.txt
z3c.dependencychecker-2.14.3.dist-info/namespace_packages.txt
z3c.dependencychecker-2.14.3.dist-info/top_level.txt
z3c.dependencychecker-2.14.3.dist-info/RECORD
