Metadata-Version: 2.1
Name: z3c.dependencychecker
Version: 2.14.3
Summary: Reports on missing or unneeded python dependencies
Home-page: https://github.com/reinout/z3c.dependencychecker
Author: Reinout van Rees
Author-email: reinout@vanrees.org
License: BSD
Keywords: dependencies requirements missing imports
Classifier: Development Status :: 5 - Production/Stable
Classifier: Environment :: Console
Classifier: Intended Audience :: Developers
Classifier: License :: OSI Approved :: BSD License
Classifier: Programming Language :: Python
Classifier: Programming Language :: Python :: 3
Classifier: Programming Language :: Python :: 3 :: Only
Classifier: Programming Language :: Python :: 3.8
Classifier: Programming Language :: Python :: 3.9
Classifier: Programming Language :: Python :: 3.10
Classifier: Programming Language :: Python :: 3.11
Classifier: Programming Language :: Python :: 3.12
Classifier: Programming Language :: Python :: Implementation :: CPython
Classifier: Programming Language :: Python :: Implementation :: PyPy
Classifier: Topic :: Software Development :: Quality Assurance
Requires-Python: >=3.8
License-File: LICENSE.rst
Requires-Dist: setuptools
Requires-Dist: cached-property
Requires-Dist: toml
Requires-Dist: stdlib-list ; python_version < "3.10"
Provides-Extra: test
Requires-Dist: pytest ; extra == 'test'
